LICENSE
README.md
setup.cfg
setup.py
NNTools.egg-info/PKG-INFO
NNTools.egg-info/SOURCES.txt
NNTools.egg-info/dependency_links.txt
NNTools.egg-info/requires.txt
NNTools.egg-info/top_level.txt
nntools/__init__.py
nntools/dataset/__init__.py
nntools/dataset/abstract_image_dataset.py
nntools/dataset/classif_dataset.py
nntools/dataset/image_dataset.py
nntools/dataset/image_tools.py
nntools/dataset/multi_image_dataset.py
nntools/dataset/seg_dataset.py
nntools/dataset/tools.py
nntools/dataset/utils.py
nntools/nnet/__init__.py
nntools/nnet/loss.py
nntools/tracker/__init__.py
nntools/tracker/log_mlflow.py
nntools/tracker/logger.py
nntools/tracker/metrics.py
nntools/tracker/tracker.py
nntools/utils/__init__.py
nntools/utils/config.py
nntools/utils/const.py
nntools/utils/io.py
nntools/utils/misc.py
nntools/utils/plotting.py
tests/test.py